chacractl/__init__.py
chacractl/decorators.py
chacractl/log.py
chacractl/main.py
chacractl/util.py
chacractl/api/__init__.py
chacractl/api/binaries.py
chacractl/api/exists.py
chacractl/api/projects.py
chacractl/api/repos.py
chacractl/tests/__init__.py
chacractl/tests/conftest.py
chacractl/tests/test_main.py
chacractl/tests/test_util.py
chacractl-0.0.25.data/scripts/chacractl
chacractl-0.0.25.dist-info/licenses/LICENSE
chacractl-0.0.25.dist-info/METADATA
chacractl-0.0.25.dist-info/WHEEL
chacractl-0.0.25.dist-info/top_level.txt
chacractl-0.0.25.dist-info/RECORD
