Metadata-Version: 2.4
Name: chacractl
Version: 0.0.25
Summary: client tool for a chacra service
Home-page: https://github.com/ceph/chacractl
Author: Alfredo Deza
Author-email: adeza@redhat.com
License: MIT
Keywords: http api chacra
Classifier: Development Status :: 4 - Beta
Classifier: Intended Audience :: Developers
Classifier: License :: OSI Approved :: MIT License
Classifier: Topic :: Software Development :: Build Tools
Classifier: Topic :: Utilities
Classifier: Operating System :: MacOS :: MacOS X
Classifier: Operating System :: POSIX
Classifier: Programming Language :: Python :: 3.10
Classifier: Programming Language :: Python :: 3.11
Classifier: Programming Language :: Python :: 3.12
License-File: LICENSE
Requires-Dist: tambo>=0.1.0
Requires-Dist: requests
Requires-Dist: requests-toolbelt
Dynamic: author
Dynamic: author-email
Dynamic: classifier
Dynamic: description
Dynamic: home-page
Dynamic: keywords
Dynamic: license
Dynamic: license-file
Dynamic: requires-dist
Dynamic: summary
